[{"model": "blog.post", "pk": 1, "fields": {"author": 1, "title": "first post", "text": "First post! \r\nTime to start programming! \r\nScary ))", "created_date": "2017-06-17T10:17:21Z", "published_date": "2017-06-17T10:17:37Z"}}, {"model": "blog.post", "pk": 2, "fields": {"author": 1, "title": "second post", "text": "Still scary, but become more interesting)\r\nFeeling exciting!", "created_date": "2017-06-17T10:17:39Z", "published_date": "2017-06-17T10:17:50Z"}}, {"model": "blog.post", "pk": 3, "fields": {"author": 1, "title": "third post", "text": "A little bit confusing about _str_... hope to figure out it soon!", "created_date": "2017-06-17T10:17:51Z", "published_date": "2017-06-17T10:18:00Z"}}, {"model": "blog.post", "pk": 4, "fields": {"author": 1, "title": "Sample title", "text": "Test", "created_date": "2017-06-17T14:34:56.660Z", "published_date": "2017-06-17T14:37:40.675Z"}}]